odoo/addons/l10n_fr_intrastat_product/README.rst
odoo/addons/l10n_fr_intrastat_product/__init__.py
odoo/addons/l10n_fr_intrastat_product/__manifest__.py
odoo/addons/l10n_fr_intrastat_product/post_install.py
odoo/addons/l10n_fr_intrastat_product/data/account_tax_template.xml
odoo/addons/l10n_fr_intrastat_product/data/deb.xsd
odoo/addons/l10n_fr_intrastat_product/data/intrastat_product_reminder.xml
odoo/addons/l10n_fr_intrastat_product/data/intrastat_transaction.xml
odoo/addons/l10n_fr_intrastat_product/demo/intrastat_demo.xml
odoo/addons/l10n_fr_intrastat_product/i18n/am.po
odoo/addons/l10n_fr_intrastat_product/i18n/bg.po
odoo/addons/l10n_fr_intrastat_product/i18n/ca.po
odoo/addons/l10n_fr_intrastat_product/i18n/da.po
odoo/addons/l10n_fr_intrastat_product/i18n/de.po
odoo/addons/l10n_fr_intrastat_product/i18n/el_GR.po
odoo/addons/l10n_fr_intrastat_product/i18n/es.po
odoo/addons/l10n_fr_intrastat_product/i18n/es_ES.po
odoo/addons/l10n_fr_intrastat_product/i18n/es_MX.po
odoo/addons/l10n_fr_intrastat_product/i18n/fi.po
odoo/addons/l10n_fr_intrastat_product/i18n/fr.po
odoo/addons/l10n_fr_intrastat_product/i18n/fr_CH.po
odoo/addons/l10n_fr_intrastat_product/i18n/gl.po
odoo/addons/l10n_fr_intrastat_product/i18n/hr.po
odoo/addons/l10n_fr_intrastat_product/i18n/it.po
odoo/addons/l10n_fr_intrastat_product/i18n/l10n_fr_intrastat_product.pot
odoo/addons/l10n_fr_intrastat_product/i18n/nb_NO.po
odoo/addons/l10n_fr_intrastat_product/i18n/nl.po
odoo/addons/l10n_fr_intrastat_product/i18n/pt.po
odoo/addons/l10n_fr_intrastat_product/i18n/pt_BR.po
odoo/addons/l10n_fr_intrastat_product/i18n/pt_PT.po
odoo/addons/l10n_fr_intrastat_product/i18n/sl.po
odoo/addons/l10n_fr_intrastat_product/i18n/tr.po
odoo/addons/l10n_fr_intrastat_product/models/__init__.py
odoo/addons/l10n_fr_intrastat_product/models/company.py
odoo/addons/l10n_fr_intrastat_product/models/intrastat_product.py
odoo/addons/l10n_fr_intrastat_product/models/intrastat_transaction.py
odoo12_addon_l10n_fr_intrastat_product-12.0.2.0.0.dist-info/METADATA
odoo12_addon_l10n_fr_intrastat_product-12.0.2.0.0.dist-info/WHEEL
odoo12_addon_l10n_fr_intrastat_product-12.0.2.0.0.dist-info/top_level.txt
odoo12_addon_l10n_fr_intrastat_product-12.0.2.0.0.dist-info/RECORD
