Metadata-Version: 2.1
Name: odoo12-addon-l10n-fr-intrastat-product
Version: 12.0.2.0.0
Summary: DEB (Déclaration d'Échange de Biens) for France
Home-page: https://github.com/OCA/l10n-france
Author: Akretion,Odoo Community Association (OCA)
Author-email: support@odoo-community.org
License: AGPL-3
Platform: UNKNOWN
Classifier: Programming Language :: Python
Classifier: Framework :: Odoo
Classifier: Framework :: Odoo :: 12.0
Classifier: License :: OSI Approved :: GNU Affero General Public License v3
Requires-Python: >=3.5
Requires-Dist: odoo12-addon-intrastat-product
Requires-Dist: odoo12-addon-l10n-fr-department
Requires-Dist: odoo (<12.1dev,>=12.0a)
